mobisurvstd/__init__.py
mobisurvstd/__main__.py
mobisurvstd/classes.py
mobisurvstd/cli.py
mobisurvstd/logger.py
mobisurvstd/main.py
mobisurvstd/utils.py
mobisurvstd/validation.py
mobisurvstd/cerema/__init__.py
mobisurvstd/cerema/common.py
mobisurvstd/cerema/deplacements.py
mobisurvstd/cerema/edgt.py
mobisurvstd/cerema/edvm.py
mobisurvstd/cerema/emc2.py
mobisurvstd/cerema/emd.py
mobisurvstd/cerema/menages.py
mobisurvstd/cerema/nantes_opendata.py
mobisurvstd/cerema/personnes.py
mobisurvstd/cerema/survey.py
mobisurvstd/cerema/trajets.py
mobisurvstd/cerema/zones.py
mobisurvstd/common/__init__.py
mobisurvstd/common/cars.py
mobisurvstd/common/clean.py
mobisurvstd/common/households.py
mobisurvstd/common/legs.py
mobisurvstd/common/motorcycles.py
mobisurvstd/common/persons.py
mobisurvstd/common/trips.py
mobisurvstd/common/zones.py
mobisurvstd/egt2010/__init__.py
mobisurvstd/egt2010/deplacements.py
mobisurvstd/egt2010/menages.py
mobisurvstd/egt2010/personnes.py
mobisurvstd/egt2010/survey.py
mobisurvstd/egt2010/trajets.py
mobisurvstd/egt2010/zones.py
mobisurvstd/egt2020/__init__.py
mobisurvstd/egt2020/deplacements.py
mobisurvstd/egt2020/menages.py
mobisurvstd/egt2020/motos.py
mobisurvstd/egt2020/personnes.py
mobisurvstd/egt2020/survey.py
mobisurvstd/egt2020/trajets.py
mobisurvstd/egt2020/voitures.py
mobisurvstd/emp/__init__.py
mobisurvstd/emp/common.py
mobisurvstd/emp/deplacements.py
mobisurvstd/emp/menages.py
mobisurvstd/emp/motos.py
mobisurvstd/emp/personnes.py
mobisurvstd/emp/survey.py
mobisurvstd/emp/voitures.py
mobisurvstd/resources/__init__.py
mobisurvstd/resources/admin_express.py
mobisurvstd/resources/insee_data.py
mobisurvstd/resources/nuts.py
mobisurvstd/schema/__init__.py
mobisurvstd/schema/cars.py
mobisurvstd/schema/common.py
mobisurvstd/schema/guarantees.py
mobisurvstd/schema/households.py
mobisurvstd/schema/legs.py
mobisurvstd/schema/motorcycles.py
mobisurvstd/schema/persons.py
mobisurvstd/schema/trips.py
mobisurvstd-1.0.1.dist-info/licenses/LICENSE.md
mobisurvstd-1.0.1.dist-info/METADATA
mobisurvstd-1.0.1.dist-info/WHEEL
mobisurvstd-1.0.1.dist-info/top_level.txt
mobisurvstd-1.0.1.dist-info/RECORD
