Metadata-Version: 2.4
Name: mobisurvstd
Version: 1.0.1
Summary: A tool to standardize French mobility survey datasets (EMC2, EGT, EMP, etc.) into a unified format.
Author-email: Lucas Javaudin <lucas@lucasjavaudin.com>
License-Expression: MIT
Project-URL: Homepage, https://github.com/MobiSurvStd/MobiSurvStd
Project-URL: Documentation, https://mobisurvstd.github.io/MobiSurvStd/index.html
Project-URL: Repository, https://github.com/MobiSurvStd/MobiSurvStd
Project-URL: Issues, https://github.com/MobiSurvStd/MobiSurvStd/issues
Keywords: mobility survey,polars,data format
Classifier: Programming Language :: Python
Classifier: Programming Language :: Python :: 3
Classifier: Topic :: File Formats
Requires-Python: >=3.10
License-File: LICENSE.md
Requires-Dist: Cartopy>=0.24.1
Requires-Dist: fastexcel>=0.14.0
Requires-Dist: fsspec>=2025.9.0
Requires-Dist: geopandas>=1.0.1
Requires-Dist: humanize>=4.13.0
Requires-Dist: loguru>=0.7.3
Requires-Dist: matplotlib>=3.10.1
Requires-Dist: numpy>=2.2.4
Requires-Dist: pandas>=2.2.3
Requires-Dist: platformdirs>=4.3.8
Requires-Dist: polars>=1.33.0
Requires-Dist: py7zr>=0.20.8
Requires-Dist: pyarrow>=19.0.1
Requires-Dist: requests>=2.32.3
Requires-Dist: typer>=0.16.0
Dynamic: license-file
